slacktools/__init__.py
slacktools/auth.py
slacktools/channel.py
slacktools/lookup.py
slacktools/misc.py
slacktools/post.py
slacktools/react.py
slacktools/slack_converter.py
slacktools/slackclient.py
slacktools/unpost.py
slacktools/unreact.py
goatslacktools-2024.7.16.1623.dist-info/METADATA
goatslacktools-2024.7.16.1623.dist-info/WHEEL
goatslacktools-2024.7.16.1623.dist-info/entry_points.txt
goatslacktools-2024.7.16.1623.dist-info/top_level.txt
goatslacktools-2024.7.16.1623.dist-info/RECORD
