Metadata-Version: 2.1
Name: goatslacktools
Version: 2024.7.16.1623
Summary: slackclient - a CLI client for GOAAT
Author-email: Chris Stacks <centerupt@gmail.com>
Classifier: Programming Language :: Python :: 3
Classifier: Operating System :: OS Independent
Requires-Python: >=3.7
Requires-Dist: slack-sdk
Requires-Dist: argparse
Requires-Dist: argcomplete
